LICENSE.txt
MANIFEST.in
README.rst
distribute_setup.py
setup.py
rapidsms_tropo.egg-info/PKG-INFO
rapidsms_tropo.egg-info/SOURCES.txt
rapidsms_tropo.egg-info/dependency_links.txt
rapidsms_tropo.egg-info/requires.txt
rapidsms_tropo.egg-info/top_level.txt
rtropo/__init__.py
rtropo/models.py
rtropo/outgoing.py
rtropo/urls.py
rtropo/views.py
rtropo/tests/__init__.py
rtropo/tests/test_exec.py
rtropo/tests/test_send.py
rtropo/tests/test_views.py
rtropo/tests/urls.py
rtropo/tests/utils.py