Metadata-Version: 1.0
Name: rapidsms-tropo
Version: 0.2.0
Summary: RapidSMS Tropo Threadless Backend
Home-page: https://github.com/caktus/rapidsms-tropo/
Author: Caktus Consulting Group
Author-email: solutions@caktusgroup.com
License: LICENSE.txt
Platform: UNKNOWN
